SPaRC_Gym/SPaRC_Gym.py
SPaRC_Gym/__init__.py
SPaRC_Gym/register_env.py
SPaRC_Gym/render/__init__.py
SPaRC_Gym/render/human_renderer.py
SPaRC_Gym/render/llm_renderer.py
sparc_gym-0.2.6.dist-info/METADATA
sparc_gym-0.2.6.dist-info/WHEEL
sparc_gym-0.2.6.dist-info/entry_points.txt
sparc_gym-0.2.6.dist-info/licenses/LICENCE
sparc_gym-0.2.6.dist-info/RECORD
