Metadata-Version: 2.4
Name: SPaRC-Gym
Version: 0.2.6
Project-URL: Repository, https://github.com/tobiTKM/SPaRC-Gym
Author-email: Tobias Mark <tobi09.mark@gmx.net>
License: MIT License
License-File: LICENCE
Requires-Python: >=3.9
Requires-Dist: chardet>=5.2.0
Requires-Dist: datasets>=4.1.1
Requires-Dist: fsspec>=2025.7.0
Requires-Dist: gymnasium>=0.28.1
Requires-Dist: huggingface-hub>=0.15.0
Requires-Dist: numpy>=1.26.4
Requires-Dist: pandas>=2.3.1
Requires-Dist: pygame>=2.2.0
Requires-Dist: pyyaml>=5.1
